documentextractor_commons/__init__.py
documentextractor_commons/models/__init__.py
documentextractor_commons/models/core/__init__.py
documentextractor_commons/models/core/file.py
documentextractor_commons/models/core/run.py
documentextractor_commons/models/core/schema.py
documentextractor_commons/models/core/workflow.py
documentextractor_commons/models/transfer/__init__.py
documentextractor_commons/models/transfer/file.py
documentextractor_commons/models/transfer/run.py
documentextractor_commons/models/transfer/schema.py
documentextractor_commons/models/transfer/workflow.py
documentextractor_commons-0.4.4.dist-info/LICENSE
documentextractor_commons-0.4.4.dist-info/METADATA
documentextractor_commons-0.4.4.dist-info/WHEEL
documentextractor_commons-0.4.4.dist-info/top_level.txt
documentextractor_commons-0.4.4.dist-info/RECORD
