Metadata-Version: 2.1
Name: documentextractor-commons
Version: 0.4.4
Summary: Common types and models for DocumentExtractor projects
Home-page: UNKNOWN
Author: Philipp Heller
Author-email: phil@documentextractor.ai
License: Apache License 2.0
Platform: UNKNOWN
Classifier: Intended Audience :: Developers
Classifier: License :: OSI Approved :: Apache Software License
Classifier: Programming Language :: Python :: 3
Classifier: Programming Language :: Python :: 3.11
Classifier: Programming Language :: Python :: 3.12
Classifier: Operating System :: OS Independent
Requires-Python: >=3.8
Requires-Dist: pydantic>=2.0
